protoRT/__init__.py
protoRT/compute_opacities.py
protoRT/disk_model.py
protoRT/rtcube.py
protoRT/data/__init__.py
protoRT/data/all_grain_sizes.txt
protoRT/data/all_wavelengths.txt
protoRT/data/axis
protoRT/data/density_cube_1.npy
protoRT/data/density_cube_2.npy
protoRT/data/kappa_abs.npy
protoRT/data/kappa_sca.npy
protort-1.0.2.dist-info/licenses/LICENSE
protort-1.0.2.dist-info/METADATA
protort-1.0.2.dist-info/WHEEL
protort-1.0.2.dist-info/top_level.txt
protort-1.0.2.dist-info/RECORD
