Metadata-Version: 2.4
Name: protoRT
Version: 1.0.2
Summary: Radiative transfer and mass analysis for planetesimal formation simulations
Home-page: https://github.com/Professor-G/protoRT
Author: Daniel Godines
Author-email: Daniel Godines <danielgodinez123@gmail.com>
License: GPL-3.0-or-later
Requires-Python: >=3.9
License-File: LICENSE
Requires-Dist: numpy
Requires-Dist: astropy>=5.0.4
Requires-Dist: scipy>=1.7.3
Requires-Dist: matplotlib>=3.5.1
Dynamic: author
Dynamic: home-page
Dynamic: license-file
Dynamic: requires-python
